pytest_datadir_mgr/__init__.py
pytest_datadir_mgr-1.3.4.dist-info/LICENSE
pytest_datadir_mgr-1.3.4.dist-info/LICENSE.artwork.txt
pytest_datadir_mgr-1.3.4.dist-info/METADATA
pytest_datadir_mgr-1.3.4.dist-info/WHEEL
pytest_datadir_mgr-1.3.4.dist-info/entry_points.txt
pytest_datadir_mgr-1.3.4.dist-info/RECORD
