Metadata-Version: 2.1
Name: pytest-datadir-mgr
Version: 1.3.4
Summary: Manager for test data: downloads, artifact caching, and a tmpdir context.
Home-page: https://github.com/joelb123/pytest-datadir-mgr
License: BSD-3-Clause
Keywords: testing,pytest-plugins,downloads,data manager,test data,software engineering
Author: Joel Berendzen
Author-email: joel@generisbio.com
Requires-Python: >=3.8,<4.0
Classifier: Development Status :: 5 - Production/Stable
Classifier: Environment :: Plugins
Classifier: Framework :: Pytest
Classifier: Intended Audience :: Developers
Classifier: License :: OSI Approved :: BSD License
Classifier: Natural Language :: English
Classifier: Operating System :: OS Independent
Classifier: Programming Language :: Python :: 3
Classifier: Programming Language :: Python :: 3.8
Classifier: Programming Language :: Python :: 3.9
Classifier: Programming Language :: Python :: 3.10
Classifier: Programming Language :: Python :: 3.11
Classifier: Programming Language :: Python :: 3.10
Classifier: Programming Language :: Python :: 3.11
Classifier: Programming Language :: Python :: 3.8
Classifier: Programming Language :: Python :: 3.9
Requires-Dist: progressbar2 (>=4.0.0)
Requires-Dist: pytest (>=7.1)
Requires-Dist: requests_download (>=0.1.2)
Project-URL: Changelog, https://github.com/joelb123/pytest-datadir-mgr/releases
